MANIFEST.in
README.md
VERSION
setup.py
../../LICENSE
simple_health_checks/middleware.py
simple_health_checks/urls.py
simple_health_checks/additional_configs/django_views_config.py
simple_health_checks/serializers/health_checks.py
simple_health_checks/views/views.py
simple_health_checks_django_views.egg-info/PKG-INFO
simple_health_checks_django_views.egg-info/SOURCES.txt
simple_health_checks_django_views.egg-info/dependency_links.txt
simple_health_checks_django_views.egg-info/requires.txt
simple_health_checks_django_views.egg-info/top_level.txt