Metadata-Version: 2.1
Name: simple-health-checks-django-views
Version: 1.0.2
Summary: Django views plugin for simple-health-checks, adds endpoints for ping and health checks
Home-page: https://gitlab.com/genomicsengland/opensource/simple-healthchecks
Author: Nicholas Dentandt, Oleg Gerasimenko, Constantina Polycarpou
Author-email: noreply@genomicsengland.co.uk
License: Apache License 2.0
Platform: UNKNOWN
Provides-Extra: tests
Provides-Extra: dev
